MANIFEST.in
README.rst
build.py
setup.py
newhope/__init__.py
newhope/cca.py
newhope/core.py
newhope/cpa.py
newhope/params.py
newhope_cffi.egg-info/PKG-INFO
newhope_cffi.egg-info/SOURCES.txt
newhope_cffi.egg-info/dependency_links.txt
newhope_cffi.egg-info/requires.txt
newhope_cffi.egg-info/top_level.txt
sources/ccakem.c
sources/ccakem.h
sources/cpakem.c
sources/cpakem.h
sources/cpapke.c
sources/cpapke.h
sources/fips202.c
sources/fips202.h
sources/ntt.c
sources/ntt.h
sources/params.h
sources/poly.c
sources/poly.h
sources/precomp.c
sources/randombytes.c
sources/randombytes.h
sources/reduce.c
sources/reduce.h
sources/verify.c
sources/verify.h