Metadata-Version: 1.1
Name: newhope-cffi
Version: 0.0.2
Summary: Tested, cross-platform Python 3 bindings for the NewHope key exchange mechanism supporting both NewHope1024-CPA-KEM and NewHope1024-CCA-KEM.
Home-page: https://github.com/kpdemetriou/newhope-cffi
Author: Phil Demetriou
Author-email: inbox@philonas.net
License: BSD
Platform: UNKNOWN
Classifier: Development Status :: 4 - Beta
Classifier: Intended Audience :: Developers
Classifier: Intended Audience :: Science/Research
Classifier: Intended Audience :: System Administrators
Classifier: Intended Audience :: Telecommunications Industry
Classifier: License :: OSI Approved :: BSD License
Classifier: Programming Language :: C
Classifier: Programming Language :: Python :: 3
Classifier: Programming Language :: Python :: 3 :: Only
Classifier: Topic :: Security
Classifier: Topic :: Security :: Cryptography
Classifier: Topic :: Utilities
